volttron/router/__init__.py
volttron/router/base_router.py
volttron/router/green_router.py
volttron/router/router.py
volttron/server/__init__.py
volttron/server/__main__.py
volttron/server/aip.py
volttron/server/async_.py
volttron/server/log_actions.py
volttron/server/monitor.py
volttron/server/scheduling.py
volttron/server/server_argparser.py
volttron/server/server_ui.py
volttron/server/serviceloader.py
volttron/server/tracking.py
volttron/server/wheel_wrap.py
volttron/services/auth/__init__.py
volttron/services/auth/auth_service.py
volttron/services/config_store/__init__.py
volttron/services/config_store/config_store_service.py
volttron/services/control/__init__.py
volttron/services/control/control_service.py
volttron/services/external/__init__.py
volttron/services/external/external_rpc_service.py
volttron/services/external/remote_discovery.py
volttron/services/health/__init__.py
volttron/services/health/health_service.py
volttron/services/peer/__init__.py
volttron/services/peer/peer_service.py
volttron/services/pubsub/__init__.py
volttron/services/pubsub/pubsub_service.py
volttron/services/routing/__init__.py
volttron/services/routing/routing_service.py
volttron/services/routing/zmq_proxy_router.py
volttron_server-0.3.12.dist-info/AUTHORS
volttron_server-0.3.12.dist-info/METADATA
volttron_server-0.3.12.dist-info/WHEEL
volttron_server-0.3.12.dist-info/entry_points.txt
volttron_server-0.3.12.dist-info/top_level.txt
volttron_server-0.3.12.dist-info/RECORD
